MANIFEST.in
README.rst
setup.cfg
setup.py
django_throttleandcache.egg-info/PKG-INFO
django_throttleandcache.egg-info/SOURCES.txt
django_throttleandcache.egg-info/dependency_links.txt
django_throttleandcache.egg-info/not-zip-safe
django_throttleandcache.egg-info/requires.txt
django_throttleandcache.egg-info/top_level.txt
tests/__init__.py
tests/celeryconfig.py
tests/settings.py
tests/test_caching.py
tests/test_regressions.py
tests/test_tdparse.py
throttleandcache/__init__.py
throttleandcache/conf.py
throttleandcache/decorators.py
throttleandcache/exceptions.py
throttleandcache/logging.py
throttleandcache/models.py
throttleandcache/pkgmeta.py
throttleandcache/tasks.py
throttleandcache/tdparse.py