Metadata-Version: 1.1
Name: django-throttleandcache
Version: 2.1.0
Summary: A utility for caching/throttling function calls.
Home-page: http://github.com/matthewwithanm/django-throttleandcache
Author: Matthew Dapena-Tretter
Author-email: m@tthewwithanm.com
License: BSD
Platform: UNKNOWN
Classifier: Environment :: Web Environment
Classifier: Framework :: Django
Classifier: Intended Audience :: Developers
Classifier: License :: OSI Approved :: BSD License
Classifier: Operating System :: OS Independent
Classifier: Programming Language :: Python
Classifier: Topic :: Internet :: WWW/HTTP
